{
  "entries": {
    "tap": {
      "caskformula/caskformula": {
        "revision": "1a0815333f5b3fb627c1a3e88572f40047f80aaa"
      },
      "d12frosted/emacs-plus": {
        "revision": "e7e0eee5fb6941bb8643f6254aba2c62a98813a3"
      },
      "github/gh": {
        "revision": "de8d7e7960fd07a5dc1abef30d754de314e26dd1"
      },
      "homebrew/bundle": {
        "revision": "110666adad626439d950b405e4164079f8068fa5"
      },
      "homebrew/cask": {
        "revision": "ff97a486e8f7a2899f07a6daba217376808c98c0"
      },
      "homebrew/core": {
        "revision": "085791ecf990b7dfe53173fc0669dd984648e9c1"
      },
      "jawshooah/pyenv": {
        "revision": "99df0b27e09c04f943527af83492f5ded4fe5ba9"
      },
      "octave-app/octave-app": {
        "revision": "1091414952b001af3a49130ac5e2a35952e7868c"
      },
      "adoptopenjdk/openjdk": {
        "revision": "8ba7c46ea725a98334d3ca2815474e4973921915"
      }
    },
    "cask": {
      "adoptopenjdk8": {
        "version": "8,265:b01",
        "options": {
          "full_name": "adoptopenjdk8"
        }
      },
      "adobe-acrobat-reader": {
        "version": "20.012.20041",
        "options": {
          "full_name": "adobe-acrobat-reader"
        }
      },
      "balenaetcher": {
        "version": "1.5.104",
        "options": {
          "full_name": "balenaetcher"
        }
      },
      "db-browser-for-sqlite": {
        "version": "3.12.0",
        "options": {
          "full_name": "db-browser-for-sqlite"
        }
      },
      "eloston-chromium": {
        "version": "84.0.4147.135-1.1",
        "options": {
          "full_name": "eloston-chromium"
        }
      },
      "fiji": {
        "version": "latest",
        "options": {
          "full_name": "fiji"
        }
      },
      "gimp": {
        "version": "2.10.14",
        "options": {
          "full_name": "gimp"
        }
      },
      "gpg-suite-no-mail": {
        "version": "2019.2",
        "options": {
          "full_name": "gpg-suite-no-mail"
        }
      },
      "iina": {
        "version": "1.0.6",
        "options": {
          "full_name": "iina"
        }
      },
      "inkscape": {
        "version": "1.0.0",
        "options": {
          "full_name": "inkscape"
        }
      },
      "karabiner-elements": {
        "version": "12.9.0",
        "options": {
          "full_name": "karabiner-elements"
        }
      },
      "libreoffice": {
        "version": "7.0.0",
        "options": {
          "full_name": "libreoffice"
        }
      },
      "mactex": {
        "version": "2020.0407",
        "options": {
          "full_name": "mactex"
        }
      },
      "notion": {
        "version": "2.0.8",
        "options": {
          "full_name": "notion"
        }
      },
      "octave-app": {
        "version": "4.4.1",
        "options": {
          "full_name": "octave-app"
        }
      },
      "postman": {
        "version": "7.22.1",
        "options": {
          "full_name": "postman"
        }
      },
      "protonmail-bridge": {
        "version": "1.3.3",
        "options": {
          "full_name": "protonmail-bridge"
        }
      },
      "protonvpn": {
        "version": "1.6.0",
        "options": {
          "full_name": "protonvpn"
        }
      },
      "sequel-pro": {
        "version": "1.1.2",
        "options": {
          "full_name": "sequel-pro"
        }
      },
      "signal": {
        "version": "1.33.1",
        "options": {
          "full_name": "signal"
        }
      },
      "superduper": {
        "version": "3.3.1,121",
        "options": {
          "full_name": "superduper"
        }
      },
      "suspicious-package": {
        "version": "3.5.3",
        "options": {
          "full_name": "suspicious-package"
        }
      },
      "texmacs": {
        "version": "1.99.13",
        "options": {
          "full_name": "texmacs"
        }
      },
      "zotero": {
        "version": "5.0.85",
        "options": {
          "full_name": "zotero"
        }
      }
    },
    "brew": {
      "gcc": {
        "version": "10.2.0",
        "bottle": {
          "cellar": "/usr/local/Cellar",
          "prefix": "/usr/local",
          "files": {
            "catalina": {
              "url": "https://homebrew.bintray.com/bottles/gcc-10.2.0.catalina.bottle.tar.gz",
              "sha256": "8dbccea194c20b1037b7e8180986e98a8ee3e37eaac12c7d223c89be3deaac6a"
            },
            "mojave": {
              "url": "https://homebrew.bintray.com/bottles/gcc-10.2.0.mojave.bottle.tar.gz",
              "sha256": "79d2293ce912dc46af961f30927b31eb06844292927be497015496f79ac41557"
            },
            "high_sierra": {
              "url": "https://homebrew.bintray.com/bottles/gcc-10.2.0.high_sierra.bottle.tar.gz",
              "sha256": "5ed870a39571614dc5d83be26d73a4164911f4356b80d9345258a4c1dc3f1b70"
            }
          }
        }
      },
      "bash": {
        "version": "5.0.18",
        "bottle": {
          "cellar": "/usr/local/Cellar",
          "prefix": "/usr/local",
          "files": {
            "catalina": {
              "url": "https://homebrew.bintray.com/bottles/bash-5.0.18.catalina.bottle.tar.gz",
              "sha256": "c6e7b7a521a1cfb21f2872bde253bfd40150bd4ba36ada62c05fcdb73ae094c6"
            },
            "mojave": {
              "url": "https://homebrew.bintray.com/bottles/bash-5.0.18.mojave.bottle.tar.gz",
              "sha256": "ba0617f6d3f4e691f9863e2f73596da94671f4c0ca21a95b99f19eced315f2d4"
            },
            "high_sierra": {
              "url": "https://homebrew.bintray.com/bottles/bash-5.0.18.high_sierra.bottle.tar.gz",
              "sha256": "46023d0bafe68b838ada45ff6a66e63f7eac814eeb84e15a09d4b84a790ef49d"
            }
          }
        }
      },
      "readline": {
        "version": "8.0.4",
        "bottle": {
          "cellar": ":any",
          "prefix": "/usr/local",
          "files": {
            "catalina": {
              "url": "https://homebrew.bintray.com/bottles/readline-8.0.4.catalina.bottle.tar.gz",
              "sha256": "6ae1c8e7c783f32bd22c6085caa4d838fed7fb386da7e40ca47b87ec9b1237d6"
            },
            "mojave": {
              "url": "https://homebrew.bintray.com/bottles/readline-8.0.4.mojave.bottle.tar.gz",
              "sha256": "29f7102a730ab39c8312cad1e7e439f6da2a67c452ce2b3380581eb185a5d8e8"
            },
            "high_sierra": {
              "url": "https://homebrew.bintray.com/bottles/readline-8.0.4.high_sierra.bottle.tar.gz",
              "sha256": "896a3d50ce8962ba56e853bdd590fadeabc00ab36475d143d6c2bea5cc15bb28"
            }
          }
        }
      },
      "xz": {
        "version": "5.2.5",
        "bottle": {
          "cellar": ":any",
          "prefix": "/usr/local",
          "files": {
            "catalina": {
              "url": "https://homebrew.bintray.com/bottles/xz-5.2.5.catalina.bottle.tar.gz",
              "sha256": "2dcc8e0121c934d1e34ffdb37fcd70f0f7b5c2f4755f2f7cbcf360e9e54cb43b"
            },
            "mojave": {
              "url": "https://homebrew.bintray.com/bottles/xz-5.2.5.mojave.bottle.tar.gz",
              "sha256": "44483961b5d2b535b0ece1936c9d40b4bc7d9c7281646cca0fb476291ab9d4dc"
            },
            "high_sierra": {
              "url": "https://homebrew.bintray.com/bottles/xz-5.2.5.high_sierra.bottle.tar.gz",
              "sha256": "1491b2b20c40c3cb0b990f520768d7e876e4ab4a7dc1da9994d0150da34ba5c6"
            }
          }
        }
      },
      "python@3.8": {
        "version": "3.8.2",
        "bottle": {
          "cellar": "/usr/local/Cellar",
          "prefix": "/usr/local",
          "files": {
            "catalina": {
              "url": "https://homebrew.bintray.com/bottles/python%403.8-3.8.5.catalina.bottle.tar.gz",
              "sha256": "3f0592dfdf6bf38c25870b57ba3e71b5b47e6c5a5ddb76aaafcbffe67eff8354"
            },
            "mojave": {
              "url": "https://homebrew.bintray.com/bottles/python%403.8-3.8.5.mojave.bottle.tar.gz",
              "sha256": "c663ffeac543b83aeae1ca13700fcb039edd57b3f0579b78fed1c2c4836ae54f"
            },
            "high_sierra": {
              "url": "https://homebrew.bintray.com/bottles/python%403.8-3.8.5.high_sierra.bottle.tar.gz",
              "sha256": "089e6eb9f410d2b8c975734df1633b847e6738f193a999f2d1f6cce82aa260b6"
            }
          }
        }
      },
      "clang-format": {
        "version": "10.0.1",
        "bottle": {
          "cellar": ":any_skip_relocation",
          "prefix": "/usr/local",
          "files": {
            "catalina": {
              "url": "https://homebrew.bintray.com/bottles/clang-format-10.0.1.catalina.bottle.tar.gz",
              "sha256": "65667bcca091df96d9f27b56a7726a41c9998ebbcd3b10bc2eb2d43aa871c216"
            },
            "mojave": {
              "url": "https://homebrew.bintray.com/bottles/clang-format-10.0.1.mojave.bottle.tar.gz",
              "sha256": "9b711f49db65634cb1dca8149804040f337ce3e68e66eeba7270c2aec66b90e0"
            },
            "high_sierra": {
              "url": "https://homebrew.bintray.com/bottles/clang-format-10.0.1.high_sierra.bottle.tar.gz",
              "sha256": "9bbc58f9d5afb228c2aeda8ea03d305d7912860f27941933d0824bee505752bd"
            }
          }
        }
      },
      "coreutils": {
        "version": "8.32",
        "bottle": {
          "cellar": "/usr/local/Cellar",
          "prefix": "/usr/local",
          "files": {
            "catalina": {
              "url": "https://homebrew.bintray.com/bottles/coreutils-8.32.catalina.bottle.tar.gz",
              "sha256": "67a4452d75a1882bd7fb977b384204edfa2758276d66290e595487922368e093"
            },
            "mojave": {
              "url": "https://homebrew.bintray.com/bottles/coreutils-8.32.mojave.bottle.tar.gz",
              "sha256": "5da6cb9dbc0a8144480dde2fb78eb0a5a1710490afc3697174f7e261ec69763f"
            },
            "high_sierra": {
              "url": "https://homebrew.bintray.com/bottles/coreutils-8.32.high_sierra.bottle.tar.gz",
              "sha256": "caa8cd8965727d0e805eccdc3e306cd0599720cdd0d5417cfcca03bead670663"
            }
          }
        }
      },
      "cowsay": {
        "version": "3.04",
        "bottle": {
          "cellar": ":any_skip_relocation",
          "prefix": "/usr/local",
          "files": {
            "catalina": {
              "url": "https://homebrew.bintray.com/bottles/cowsay-3.04.catalina.bottle.tar.gz",
              "sha256": "f6cb1c4d1b6f9d8eff3630420c8e51cb51029d00261fa30513f915ff231f5e2d"
            },
            "mojave": {
              "url": "https://homebrew.bintray.com/bottles/cowsay-3.04.mojave.bottle.tar.gz",
              "sha256": "bff466bf07d7aba50b954b4b37b15eb338da542244450843ed6f1fd8223a5eab"
            },
            "high_sierra": {
              "url": "https://homebrew.bintray.com/bottles/cowsay-3.04.high_sierra.bottle.tar.gz",
              "sha256": "9dd1c2263533507d55a6cfc8747ad6a68c0c042c7631512f0611001831dd441c"
            },
            "sierra": {
              "url": "https://homebrew.bintray.com/bottles/cowsay-3.04.sierra.bottle.tar.gz",
              "sha256": "17a1a4620885c9a4b7104b43072ed32348b37f6bb43a1120fe23a46d893e87ea"
            },
            "el_capitan": {
              "url": "https://homebrew.bintray.com/bottles/cowsay-3.04.el_capitan.bottle.tar.gz",
              "sha256": "360390af15a3c4793e07eda95f55f4a5466ffafc766cb6b62f9790146080a62a"
            },
            "yosemite": {
              "url": "https://homebrew.bintray.com/bottles/cowsay-3.04.yosemite.bottle.tar.gz",
              "sha256": "a622af361a6139bc930b371fbde7cfc54bbe8bebfbbe0782e59248fadb10b95f"
            },
            "mavericks": {
              "url": "https://homebrew.bintray.com/bottles/cowsay-3.04.mavericks.bottle.tar.gz",
              "sha256": "185bfafd379cd6f6d6202fdae0750fdd2998cc94f33ea349bd4872a0274cb1dc"
            }
          }
        }
      },
      "docker": {
        "version": "19.03.12",
        "bottle": {
          "cellar": ":any_skip_relocation",
          "prefix": "/usr/local",
          "files": {
            "catalina": {
              "url": "https://homebrew.bintray.com/bottles/docker-19.03.12.catalina.bottle.1.tar.gz",
              "sha256": "ce26e2a26692cd22ad6c37edbae304e2349f98682f51fc8e5c1ae074fa9573fc"
            },
            "mojave": {
              "url": "https://homebrew.bintray.com/bottles/docker-19.03.12.mojave.bottle.1.tar.gz",
              "sha256": "be8241ad433dd7c8a5c9b73344f4e24f0bc4b4808f4a33b99811ea403d0d0159"
            },
            "high_sierra": {
              "url": "https://homebrew.bintray.com/bottles/docker-19.03.12.high_sierra.bottle.1.tar.gz",
              "sha256": "ac92b86b4f792d61be6c0d90549a3633e071c4a6833d696b8a285b3be90962f7"
            }
          }
        }
      },
      "ghostscript": {
        "version": "9.52",
        "bottle": {
          "cellar": "/usr/local/Cellar",
          "prefix": "/usr/local",
          "files": {
            "catalina": {
              "url": "https://homebrew.bintray.com/bottles/ghostscript-9.52.catalina.bottle.tar.gz",
              "sha256": "8cd0efa1e5525f849be3ee1e50e1635b99667cb4d1eb6c3002a45378346882f4"
            },
            "mojave": {
              "url": "https://homebrew.bintray.com/bottles/ghostscript-9.52.mojave.bottle.tar.gz",
              "sha256": "8906a4dbf2513963a4710f351e3426622c259bd888c760e4c08a9436860b4014"
            },
            "high_sierra": {
              "url": "https://homebrew.bintray.com/bottles/ghostscript-9.52.high_sierra.bottle.tar.gz",
              "sha256": "cd5e55d0429d7e88ba2d580e79934c157d5bd2981d71a7f40db4573abe79af67"
            }
          }
        }
      },
      "libidn2": {
        "version": "2.3.0",
        "bottle": {
          "cellar": "/usr/local/Cellar",
          "prefix": "/usr/local",
          "files": {
            "catalina": {
              "url": "https://homebrew.bintray.com/bottles/libidn2-2.3.0.catalina.bottle.tar.gz",
              "sha256": "0908585cca518a83f101b2edc0417a26a4b4fc8b76e393c6f6672de6e595c914"
            },
            "mojave": {
              "url": "https://homebrew.bintray.com/bottles/libidn2-2.3.0.mojave.bottle.tar.gz",
              "sha256": "d56e7ff347b0a4c2c433cd44564dfef74c9f1b237ef913307e152314677e1360"
            },
            "high_sierra": {
              "url": "https://homebrew.bintray.com/bottles/libidn2-2.3.0.high_sierra.bottle.tar.gz",
              "sha256": "4530dd74cbd31c49b0f499eda0f9ea29ec7ff6ae00f9aff3974247365d1fb21e"
            }
          }
        }
      },
      "tesseract": {
        "version": "4.1.1",
        "bottle": {
          "cellar": ":any",
          "prefix": "/usr/local",
          "files": {
            "catalina": {
              "url": "https://homebrew.bintray.com/bottles/tesseract-4.1.1.catalina.bottle.tar.gz",
              "sha256": "81ff467946d9c85151c86819034cd183a983b4a3fa10374c7f039a5ec3ef0d82"
            },
            "mojave": {
              "url": "https://homebrew.bintray.com/bottles/tesseract-4.1.1.mojave.bottle.tar.gz",
              "sha256": "34eee505fccec07eaab30f14c46f9688db9f3aa578306d47bbcd31801b0b849d"
            },
            "high_sierra": {
              "url": "https://homebrew.bintray.com/bottles/tesseract-4.1.1.high_sierra.bottle.tar.gz",
              "sha256": "6b64585454bcca9b62945b284000723d76afad15b5e80109ca6cdc699ae50e25"
            }
          }
        }
      },
      "ffmpeg": {
        "version": "4.3.1",
        "bottle": {
          "cellar": "/usr/local/Cellar",
          "prefix": "/usr/local",
          "files": {
            "catalina": {
              "url": "https://homebrew.bintray.com/bottles/ffmpeg-4.3.1.catalina.bottle.tar.gz",
              "sha256": "45a432a330239f38a11c77a0decd32b44b80d77669ca73eff4ed93b257569a3a"
            },
            "mojave": {
              "url": "https://homebrew.bintray.com/bottles/ffmpeg-4.3.1.mojave.bottle.tar.gz",
              "sha256": "87d27a92d7d5ebfbdd3ada8f658d34c81a300352ce68d995e29b389ba773c49f"
            },
            "high_sierra": {
              "url": "https://homebrew.bintray.com/bottles/ffmpeg-4.3.1.high_sierra.bottle.tar.gz",
              "sha256": "9566b4ca9d24ab172295cb9a348af359e67b0620ef2e92ac579444549cf67870"
            }
          }
        }
      },
      "fortune": {
        "version": "9708",
        "bottle": {
          "cellar": "/usr/local/Cellar",
          "prefix": "/usr/local",
          "files": {
            "catalina": {
              "url": "https://homebrew.bintray.com/bottles/fortune-9708.catalina.bottle.3.tar.gz",
              "sha256": "bde8e2f3f2e9e65c18b72b647cd8aad7658251592fae03717e7d90f4428464de"
            },
            "mojave": {
              "url": "https://homebrew.bintray.com/bottles/fortune-9708.mojave.bottle.3.tar.gz",
              "sha256": "f635d0fc0504922ba1bfae451f17b874ea96cffb85dead0913adb9da0669738e"
            },
            "high_sierra": {
              "url": "https://homebrew.bintray.com/bottles/fortune-9708.high_sierra.bottle.3.tar.gz",
              "sha256": "b650a61e6b39e9f12179140e0d2b23c0c606e7f29e64851aac5df4e376d77130"
            },
            "sierra": {
              "url": "https://homebrew.bintray.com/bottles/fortune-9708.sierra.bottle.3.tar.gz",
              "sha256": "c6fe1b893c31bc71b2c24de5bcc0a84fbd5025091d796250a7ef4ff6e406eea7"
            }
          }
        }
      },
      "gdb": {
        "version": "9.2_1",
        "bottle": {
          "cellar": "/usr/local/Cellar",
          "prefix": "/usr/local",
          "files": {
            "catalina": {
              "url": "https://homebrew.bintray.com/bottles/gdb-9.2_1.catalina.bottle.tar.gz",
              "sha256": "fbfb5bb6a5f8d7edb33937ebd505fbfe5074db3d49a0403803edafcbcbde297f"
            },
            "mojave": {
              "url": "https://homebrew.bintray.com/bottles/gdb-9.2_1.mojave.bottle.tar.gz",
              "sha256": "64fdeef2403ae8dad106d4933dc6b5c555d560249a18dccc0a518c53f8ea26b1"
            },
            "high_sierra": {
              "url": "https://homebrew.bintray.com/bottles/gdb-9.2_1.high_sierra.bottle.tar.gz",
              "sha256": "cbf828704099f07e8c863c962ef8deb60b932e3d75146a16b20967e3ddca7cbe"
            }
          }
        }
      },
      "git": {
        "version": "2.28.0",
        "bottle": {
          "cellar": "/usr/local/Cellar",
          "prefix": "/usr/local",
          "files": {
            "catalina": {
              "url": "https://homebrew.bintray.com/bottles/git-2.28.0.catalina.bottle.tar.gz",
              "sha256": "6c4d10f29f78dcbefa12fab3e47e7755d5d2ca2e9bbc5aeee4838ad223296d0a"
            },
            "mojave": {
              "url": "https://homebrew.bintray.com/bottles/git-2.28.0.mojave.bottle.tar.gz",
              "sha256": "10f23bc63568fdeb598df2dd30fbb0ead31f2eef3c0990a8ac53f3e2005de82f"
            },
            "high_sierra": {
              "url": "https://homebrew.bintray.com/bottles/git-2.28.0.high_sierra.bottle.tar.gz",
              "sha256": "5095b064dfafb8cf4cabd017844f181d8eabaf45fb6965d2d30ed6de00c0e884"
            }
          }
        }
      },
      "gnu-tar": {
        "version": "1.32",
        "bottle": {
          "cellar": ":any_skip_relocation",
          "prefix": "/usr/local",
          "files": {
            "catalina": {
              "url": "https://homebrew.bintray.com/bottles/gnu-tar-1.32.catalina.bottle.1.tar.gz",
              "sha256": "158cb67ea9e02435d671013b4d0d7369822758d9f7ff400ce2512a03f2f7f4e4"
            },
            "mojave": {
              "url": "https://homebrew.bintray.com/bottles/gnu-tar-1.32.mojave.bottle.1.tar.gz",
              "sha256": "1034894e78bb22b0fcf0c8114666d4dc3eb82345a5ca83797ca3bda367d998ac"
            },
            "high_sierra": {
              "url": "https://homebrew.bintray.com/bottles/gnu-tar-1.32.high_sierra.bottle.1.tar.gz",
              "sha256": "3771cead286229786d9d92a7697bc6e0de576ec9cae1f881017884ceb3e24f17"
            }
          }
        }
      },
      "go": {
        "version": "1.15",
        "bottle": {
          "cellar": "/usr/local/Cellar",
          "prefix": "/usr/local",
          "files": {
            "catalina": {
              "url": "https://homebrew.bintray.com/bottles/go-1.15.catalina.bottle.tar.gz",
              "sha256": "36ef2e4cc3ecc84e0c1e98580a63f8d417efc8831f0c59b0a7e13d517c61353b"
            },
            "mojave": {
              "url": "https://homebrew.bintray.com/bottles/go-1.15.mojave.bottle.tar.gz",
              "sha256": "ea373dd668c31caa9816a5028028694425635cc3871783709381d872906fa78e"
            },
            "high_sierra": {
              "url": "https://homebrew.bintray.com/bottles/go-1.15.high_sierra.bottle.tar.gz",
              "sha256": "a29ea808ffac13d3967dee44f30a9f72709b941f7e82836715f939970e6cb222"
            }
          }
        }
      },
      "htop": {
        "version": "2.2.0_1",
        "bottle": {
          "cellar": ":any",
          "prefix": "/usr/local",
          "files": {
            "catalina": {
              "url": "https://homebrew.bintray.com/bottles/htop-2.2.0_1.catalina.bottle.tar.gz",
              "sha256": "c06ff60960f64f5c8395f53d7419cbcce2a22ee87f0cb0138352c8a88111d21c"
            },
            "mojave": {
              "url": "https://homebrew.bintray.com/bottles/htop-2.2.0_1.mojave.bottle.tar.gz",
              "sha256": "77aa302765353b4085dcad52356d3264183e06310dda8d5bac64642299ea2902"
            },
            "high_sierra": {
              "url": "https://homebrew.bintray.com/bottles/htop-2.2.0_1.high_sierra.bottle.tar.gz",
              "sha256": "0ebfb655b91566ba31f8effc94d642a43305ff95bdc9b30b46fadc132e2ced0c"
            },
            "sierra": {
              "url": "https://homebrew.bintray.com/bottles/htop-2.2.0_1.sierra.bottle.tar.gz",
              "sha256": "ed93b86f011de155c5d261b8c9cc9cb81fd0017667bf3ebe26ee090716bcd650"
            }
          }
        }
      },
      "imagemagick": {
        "version": "7.0.10-14",
        "bottle": {
          "cellar": "/usr/local/Cellar",
          "prefix": "/usr/local",
          "files": {
            "catalina": {
              "url": "https://homebrew.bintray.com/bottles/imagemagick-7.0.10-28.catalina.bottle.tar.gz",
              "sha256": "3e0d544ec925c0e5c75ab6457b9dc11bc42bff58f2c62e12be7019de002abb67"
            },
            "mojave": {
              "url": "https://homebrew.bintray.com/bottles/imagemagick-7.0.10-28.mojave.bottle.tar.gz",
              "sha256": "00ba5b5569fa5d2d0b31cfe54967be45d75887c3479b04519cc776fd27bb1741"
            },
            "high_sierra": {
              "url": "https://homebrew.bintray.com/bottles/imagemagick-7.0.10-28.high_sierra.bottle.tar.gz",
              "sha256": "68e4425022c6bc1813d830c7b042c8b17aaf8e62d896fc42d2caa7264064cbc1"
            }
          }
        }
      },
      "ispell": {
        "version": "3.4.00",
        "bottle": {
          "cellar": "/usr/local/Cellar",
          "prefix": "/usr/local",
          "files": {
            "catalina": {
              "url": "https://homebrew.bintray.com/bottles/ispell-3.4.00.catalina.bottle.tar.gz",
              "sha256": "c4a726692b88e792bd82ee0b4cd527e8f69ab0a244f839486087e2b291947afe"
            },
            "mojave": {
              "url": "https://homebrew.bintray.com/bottles/ispell-3.4.00.mojave.bottle.tar.gz",
              "sha256": "5e4a1b0bd20714be296012b2b90c7bb92bfa01b997a4d4efccc369b9553a8eb8"
            },
            "high_sierra": {
              "url": "https://homebrew.bintray.com/bottles/ispell-3.4.00.high_sierra.bottle.tar.gz",
              "sha256": "67142ae321c800cc9f4941e8d4e665f195dad06cc483cde11d51fed7a0cde426"
            },
            "sierra": {
              "url": "https://homebrew.bintray.com/bottles/ispell-3.4.00.sierra.bottle.tar.gz",
              "sha256": "697a51b2d4e5d568ef18fdfe5943691a534145829522e3d4bb7d25f2f7978c9f"
            },
            "el_capitan": {
              "url": "https://homebrew.bintray.com/bottles/ispell-3.4.00.el_capitan.bottle.tar.gz",
              "sha256": "81d9f6f9aca0f92ba3bece2ad22d0b0bca29c719304c6c5e8e59b02a3c8763da"
            },
            "yosemite": {
              "url": "https://homebrew.bintray.com/bottles/ispell-3.4.00.yosemite.bottle.tar.gz",
              "sha256": "ff46baf7aa6daf42fddde68897bd80dbb073922b4556c502e7b0072656b48498"
            },
            "mavericks": {
              "url": "https://homebrew.bintray.com/bottles/ispell-3.4.00.mavericks.bottle.tar.gz",
              "sha256": "f1ee90dcc76682d17c2b758d2a896493448753acc0e556e9b0c8bf7ec0f552df"
            }
          }
        }
      },
      "latex2html": {
        "version": "2020.2",
        "bottle": {
          "cellar": ":any_skip_relocation",
          "prefix": "/usr/local",
          "files": {
            "catalina": {
              "url": "https://homebrew.bintray.com/bottles/latex2html-2020.2.catalina.bottle.tar.gz",
              "sha256": "f5448ddd27e175bc6cf388581f3332a188bc52a15c69d41b8002cc5303471cf4"
            },
            "mojave": {
              "url": "https://homebrew.bintray.com/bottles/latex2html-2020.2.mojave.bottle.tar.gz",
              "sha256": "fc170658ac170d9bf484a05d99fc052fdefdf9d39ada1cb0b2cffa20950e7ed5"
            },
            "high_sierra": {
              "url": "https://homebrew.bintray.com/bottles/latex2html-2020.2.high_sierra.bottle.tar.gz",
              "sha256": "1057bbb3c6c991e3ce62425b2b11852558d40be5fab478560784ee2b60ec2591"
            }
          }
        }
      },
      "markdown": {
        "version": "1.0.1",
        "bottle": {
          "cellar": ":any_skip_relocation",
          "prefix": "/usr/local",
          "files": {
            "catalina": {
              "url": "https://homebrew.bintray.com/bottles/markdown-1.0.1.catalina.bottle.tar.gz",
              "sha256": "35864422386d1390de813462b697b604813bc3a7caac7bf3fd172335e25b2a55"
            },
            "mojave": {
              "url": "https://homebrew.bintray.com/bottles/markdown-1.0.1.mojave.bottle.tar.gz",
              "sha256": "343d406a2a4838499afa96395733e0d61f91c725a4693e6c5b3c49293e5297e8"
            },
            "high_sierra": {
              "url": "https://homebrew.bintray.com/bottles/markdown-1.0.1.high_sierra.bottle.tar.gz",
              "sha256": "c7b43e96e9967731f9f9395152dca0d1535eb270a953aeccfe24dc99d3941f97"
            },
            "sierra": {
              "url": "https://homebrew.bintray.com/bottles/markdown-1.0.1.sierra.bottle.tar.gz",
              "sha256": "47715f7beb1f434a5d52e6977c7f6ad584be7b0d970dacb00ef5965bd162858d"
            },
            "el_capitan": {
              "url": "https://homebrew.bintray.com/bottles/markdown-1.0.1.el_capitan.bottle.tar.gz",
              "sha256": "a5b025bc09c8b274507cfc5c86da6350560477f24ce109dd5a79f2dafa97d805"
            },
            "yosemite": {
              "url": "https://homebrew.bintray.com/bottles/markdown-1.0.1.yosemite.bottle.tar.gz",
              "sha256": "5e1b8b5388f1b4ceefe3fae528ae83e2fa3f9ed9f27668e8faded36b9ec3274e"
            },
            "mavericks": {
              "url": "https://homebrew.bintray.com/bottles/markdown-1.0.1.mavericks.bottle.tar.gz",
              "sha256": "66fffda1a29fd9e2dcddcb52fb9606f21d897bf4680583626b612a95d27b1e04"
            }
          }
        }
      },
      "maven": {
        "version": "3.6.3_1",
        "bottle": false
      },
      "mercurial": {
        "version": "5.5",
        "bottle": {
          "cellar": "/usr/local/Cellar",
          "prefix": "/usr/local",
          "files": {
            "catalina": {
              "url": "https://homebrew.bintray.com/bottles/mercurial-5.5.catalina.bottle.tar.gz",
              "sha256": "99cd39e3f4bd9bbfc94b191d4c73276da4e174f0bd4043de96737c2b91c1bfe8"
            },
            "mojave": {
              "url": "https://homebrew.bintray.com/bottles/mercurial-5.5.mojave.bottle.tar.gz",
              "sha256": "a0e0763833b37b8731e2555c99c7a96825df7ab2c978f912b4bb17b87d0f8bcd"
            },
            "high_sierra": {
              "url": "https://homebrew.bintray.com/bottles/mercurial-5.5.high_sierra.bottle.tar.gz",
              "sha256": "5477a3357f4e2345d626cb5dfe5f090f3765d24100aec70af9c958c5fd6338c0"
            }
          }
        }
      },
      "nmap": {
        "version": "7.80_1",
        "bottle": {
          "cellar": "/usr/local/Cellar",
          "prefix": "/usr/local",
          "files": {
            "catalina": {
              "url": "https://homebrew.bintray.com/bottles/nmap-7.80_1.catalina.bottle.1.tar.gz",
              "sha256": "e1ba8b92c348e3d04c89f4ffc50800d480dd45ca34726a4f7e3fe7974b0bb651"
            },
            "mojave": {
              "url": "https://homebrew.bintray.com/bottles/nmap-7.80_1.mojave.bottle.1.tar.gz",
              "sha256": "fb166b6d77a7a1df2a38a58f5123d51bd3ace308c736094c2c9b5a2591f405ee"
            },
            "high_sierra": {
              "url": "https://homebrew.bintray.com/bottles/nmap-7.80_1.high_sierra.bottle.1.tar.gz",
              "sha256": "8edad05b0f4fc20552dd6c1b573a7fa6bf2d03568b014ee60c1153980fb43649"
            }
          }
        }
      },
      "node": {
        "version": "14.8.0",
        "bottle": {
          "cellar": ":any",
          "prefix": "/usr/local",
          "files": {
            "catalina": {
              "url": "https://homebrew.bintray.com/bottles/node-14.8.0.catalina.bottle.tar.gz",
              "sha256": "ec85b0f1a6b5ab229ee1445ca604f6455e15dfa632efdb79839296e5c2fc6631"
            },
            "mojave": {
              "url": "https://homebrew.bintray.com/bottles/node-14.8.0.mojave.bottle.tar.gz",
              "sha256": "5e2de72f9e1fc18df29226a40ae6efe39bff083f1f91d765c5dbd9db308613ae"
            },
            "high_sierra": {
              "url": "https://homebrew.bintray.com/bottles/node-14.8.0.high_sierra.bottle.tar.gz",
              "sha256": "7129555cbbde75ed026b19506fb6f5184545a0ac30121cce63ab92d4310b99a3"
            }
          }
        }
      },
      "pstoedit": {
        "version": "3.75",
        "bottle": {
          "cellar": "/usr/local/Cellar",
          "prefix": "/usr/local",
          "files": {
            "catalina": {
              "url": "https://homebrew.bintray.com/bottles/pstoedit-3.75.catalina.bottle.tar.gz",
              "sha256": "f048d902c088f0625c0c9e18d84b159493775b40e742812b040e7b517900260a"
            },
            "mojave": {
              "url": "https://homebrew.bintray.com/bottles/pstoedit-3.75.mojave.bottle.tar.gz",
              "sha256": "1f3ec91e58d95e08081694b43e031ed83f13a73cecff15c55c532268282b0ad1"
            },
            "high_sierra": {
              "url": "https://homebrew.bintray.com/bottles/pstoedit-3.75.high_sierra.bottle.tar.gz",
              "sha256": "22710dd8997d40cec3492c40960a9966b80b386bdbd3fed46515c66bb25053d7"
            }
          }
        }
      },
      "octave": {
        "version": "5.2.0_9",
        "bottle": {
          "cellar": "/usr/local/Cellar",
          "prefix": "/usr/local",
          "files": {
            "catalina": {
              "url": "https://homebrew.bintray.com/bottles/octave-5.2.0_9.catalina.bottle.tar.gz",
              "sha256": "5c9af6d3f0f61cd764067c1f66997b0044788dc76e8ddc28c6f64194a275d09c"
            },
            "mojave": {
              "url": "https://homebrew.bintray.com/bottles/octave-5.2.0_9.mojave.bottle.tar.gz",
              "sha256": "37389123fb6ec5bda0ef8874596231b6e22a20d60ce9cb792a97c18bff7f307f"
            },
            "high_sierra": {
              "url": "https://homebrew.bintray.com/bottles/octave-5.2.0_9.high_sierra.bottle.tar.gz",
              "sha256": "e44de6cb9315e2f125ea516733513c048b38fd9c77719eb270717daff43360a6"
            }
          }
        }
      },
      "osx-cpu-temp": {
        "version": "1.1.0",
        "bottle": {
          "cellar": ":any_skip_relocation",
          "prefix": "/usr/local",
          "files": {
            "catalina": {
              "url": "https://homebrew.bintray.com/bottles/osx-cpu-temp-1.1.0.catalina.bottle.tar.gz",
              "sha256": "e1df41402ed817941f591a5cc094fe4491b092de8d5177dd363eccecff811bec"
            },
            "mojave": {
              "url": "https://homebrew.bintray.com/bottles/osx-cpu-temp-1.1.0.mojave.bottle.tar.gz",
              "sha256": "c0301d2c47c23bc8ed0042fbaf447e82ca8dbbf10b1939d9a4f684961a24d0d2"
            },
            "high_sierra": {
              "url": "https://homebrew.bintray.com/bottles/osx-cpu-temp-1.1.0.high_sierra.bottle.tar.gz",
              "sha256": "2255aa28242ce07a62fc0eabaf146592fb70745e641cfc775a21f99841cec625"
            },
            "sierra": {
              "url": "https://homebrew.bintray.com/bottles/osx-cpu-temp-1.1.0.sierra.bottle.tar.gz",
              "sha256": "d68a47b126eaee8f75d281785322877055187f89540eb2744b9cd4da15ca6a69"
            }
          }
        }
      },
      "pandoc": {
        "version": "2.10.1",
        "bottle": {
          "cellar": ":any_skip_relocation",
          "prefix": "/usr/local",
          "files": {
            "catalina": {
              "url": "https://homebrew.bintray.com/bottles/pandoc-2.10.1.catalina.bottle.1.tar.gz",
              "sha256": "720d055d2bdafbe818f50e186e710f7a8178719b56cfafa1d1948af16df7d7ea"
            },
            "mojave": {
              "url": "https://homebrew.bintray.com/bottles/pandoc-2.10.1.mojave.bottle.1.tar.gz",
              "sha256": "7174b62811cd4d4116bcb5edcfb55793f733e39ad79d8e8914a8b5e2c71f2b78"
            },
            "high_sierra": {
              "url": "https://homebrew.bintray.com/bottles/pandoc-2.10.1.high_sierra.bottle.1.tar.gz",
              "sha256": "ef823fe9876a5a6c3fe25db6b8dbca7b372320f7e6f5c5b224a7696acf5c397b"
            }
          }
        }
      },
      "poppler": {
        "version": "0.90.1",
        "bottle": {
          "cellar": "/usr/local/Cellar",
          "prefix": "/usr/local",
          "files": {
            "catalina": {
              "url": "https://homebrew.bintray.com/bottles/poppler-0.90.1.catalina.bottle.tar.gz",
              "sha256": "da177ae8a0478d5886e2ee2ea6db51d22affaf9aac400d636b28c65e780176fd"
            },
            "mojave": {
              "url": "https://homebrew.bintray.com/bottles/poppler-0.90.1.mojave.bottle.tar.gz",
              "sha256": "c00b51e54bbaecba8c74aa4df838614bdd72e73269e4152eaceba062c835cfbf"
            },
            "high_sierra": {
              "url": "https://homebrew.bintray.com/bottles/poppler-0.90.1.high_sierra.bottle.tar.gz",
              "sha256": "21aef53bc7084c87517494130f2d116a247d14276fbc36707b3655038320de40"
            }
          }
        }
      },
      "pdf2svg": {
        "version": "0.2.3_5",
        "bottle": {
          "cellar": ":any",
          "prefix": "/usr/local",
          "files": {
            "catalina": {
              "url": "https://homebrew.bintray.com/bottles/pdf2svg-0.2.3_5.catalina.bottle.tar.gz",
              "sha256": "8350da4f06838454cf26788b9ea27cbd9255d567be906d4fde5dea332b035734"
            },
            "mojave": {
              "url": "https://homebrew.bintray.com/bottles/pdf2svg-0.2.3_5.mojave.bottle.tar.gz",
              "sha256": "3999f52a6638bd2090feabd62cf91112a6b98bf6577a112771941ec6781eabd8"
            },
            "high_sierra": {
              "url": "https://homebrew.bintray.com/bottles/pdf2svg-0.2.3_5.high_sierra.bottle.tar.gz",
              "sha256": "9477928316e8a5cb7edc7d03568a22a2f2fb87e1440a96e100c79695c1b5cde9"
            },
            "sierra": {
              "url": "https://homebrew.bintray.com/bottles/pdf2svg-0.2.3_5.sierra.bottle.tar.gz",
              "sha256": "ec7f985d7a62787268265f4e05c87d59926a7f242c22972e32418e7cfaa5448e"
            }
          }
        }
      },
      "pyenv": {
        "version": "1.2.20",
        "bottle": {
          "cellar": ":any",
          "prefix": "/usr/local",
          "files": {
            "catalina": {
              "url": "https://homebrew.bintray.com/bottles/pyenv-1.2.20.catalina.bottle.tar.gz",
              "sha256": "74e2f3a7cf6513948cbac05f3af8f3f2ae7df825dfc21a91759963afbb398420"
            },
            "mojave": {
              "url": "https://homebrew.bintray.com/bottles/pyenv-1.2.20.mojave.bottle.tar.gz",
              "sha256": "ac4f0bdd6bba22dd590ce2b2e86ee51300c3bb708288bc26e6294e1035a38a03"
            },
            "high_sierra": {
              "url": "https://homebrew.bintray.com/bottles/pyenv-1.2.20.high_sierra.bottle.tar.gz",
              "sha256": "608b5e27568abc7c326c0bb066cf6d188c829362dd0dff718a04a44e9082f82a"
            }
          }
        }
      },
      "pyenv-ccache": {
        "version": "0.0.2",
        "bottle": false
      },
      "python@2": {
        "version": "2.7.17_1",
        "bottle": false
      },
      "rbenv": {
        "version": "1.1.2",
        "bottle": {
          "cellar": ":any",
          "prefix": "/usr/local",
          "files": {
            "catalina": {
              "url": "https://homebrew.bintray.com/bottles/rbenv-1.1.2.catalina.bottle.tar.gz",
              "sha256": "503ed6d818502f00f031b9f49461934e252b9bfba2876e90a326fc27bb1052d6"
            },
            "mojave": {
              "url": "https://homebrew.bintray.com/bottles/rbenv-1.1.2.mojave.bottle.tar.gz",
              "sha256": "d1019098dee8d037587069398e5ad04e6d736f834dc44ae73943bec46b10b260"
            },
            "high_sierra": {
              "url": "https://homebrew.bintray.com/bottles/rbenv-1.1.2.high_sierra.bottle.tar.gz",
              "sha256": "b5984102794a9d39388ca1f6ec77965aeea29b971cc00cb5af8ede8ee6c926d6"
            },
            "sierra": {
              "url": "https://homebrew.bintray.com/bottles/rbenv-1.1.2.sierra.bottle.tar.gz",
              "sha256": "873175a851e5aa4f5b3438072030b945c252f08a9a07760c64dc045e2cce4724"
            }
          }
        }
      },
      "ripgrep": {
        "version": "12.1.1",
        "bottle": {
          "cellar": ":any",
          "prefix": "/usr/local",
          "files": {
            "catalina": {
              "url": "https://homebrew.bintray.com/bottles/ripgrep-12.1.1.catalina.bottle.tar.gz",
              "sha256": "60460d422253113af3ed60332104f309638942821c655332211a6bc2213c472c"
            },
            "mojave": {
              "url": "https://homebrew.bintray.com/bottles/ripgrep-12.1.1.mojave.bottle.tar.gz",
              "sha256": "de4b18789f5d9bc4aaa4d906501200ae4ece7a1971dd1b86e2b2d0a2c8e0d764"
            },
            "high_sierra": {
              "url": "https://homebrew.bintray.com/bottles/ripgrep-12.1.1.high_sierra.bottle.tar.gz",
              "sha256": "cfea5335bf4eccfb7cd1d93bec234d96bd49dce8d593ea966687f777909ba291"
            }
          }
        }
      },
      "rsync": {
        "version": "3.2.3",
        "bottle": {
          "cellar": ":any",
          "prefix": "/usr/local",
          "files": {
            "catalina": {
              "url": "https://homebrew.bintray.com/bottles/rsync-3.2.3.catalina.bottle.tar.gz",
              "sha256": "fd92045e16b9b83ab6c281a1e658e27731ef9af53fcb6bb7ce6b9533851e728e"
            },
            "mojave": {
              "url": "https://homebrew.bintray.com/bottles/rsync-3.2.3.mojave.bottle.tar.gz",
              "sha256": "1be1e9754c4f4a4b043aece33299d90f50d01274682f63c29eca7d9bcb8a2090"
            },
            "high_sierra": {
              "url": "https://homebrew.bintray.com/bottles/rsync-3.2.3.high_sierra.bottle.tar.gz",
              "sha256": "5cf9c6e0014687c4abb4044e7f5e12d5d453b81c5dbadd472438b4131c655a1f"
            }
          }
        }
      },
      "shellcheck": {
        "version": "0.7.1",
        "bottle": {
          "cellar": ":any_skip_relocation",
          "prefix": "/usr/local",
          "files": {
            "catalina": {
              "url": "https://homebrew.bintray.com/bottles/shellcheck-0.7.1.catalina.bottle.1.tar.gz",
              "sha256": "0cd635d2172d5e6617be8cdfb2723b6aa6feb2aa22e36cb3172d8b6fa012f4a0"
            },
            "mojave": {
              "url": "https://homebrew.bintray.com/bottles/shellcheck-0.7.1.mojave.bottle.1.tar.gz",
              "sha256": "37201a49c0d7a5be49c5d97d4f6f8f5fcfef7d700b4694f74648a1addcd6783d"
            },
            "high_sierra": {
              "url": "https://homebrew.bintray.com/bottles/shellcheck-0.7.1.high_sierra.bottle.1.tar.gz",
              "sha256": "1b20aeaba4d5e2e3df5cbe27636d655b6f877ee05a41d25fe1e0b3f9d00afa81"
            }
          }
        }
      },
      "tcl-tk": {
        "version": "8.6.10",
        "bottle": {
          "cellar": "/usr/local/Cellar",
          "prefix": "/usr/local",
          "files": {
            "catalina": {
              "url": "https://homebrew.bintray.com/bottles/tcl-tk-8.6.10.catalina.bottle.1.tar.gz",
              "sha256": "4740b30b97f0308ecc59c1308945c38ddca5d3da528d779f38199a2dad905fa1"
            },
            "mojave": {
              "url": "https://homebrew.bintray.com/bottles/tcl-tk-8.6.10.mojave.bottle.1.tar.gz",
              "sha256": "1851fee12a3ee44648845d8663a192712ce6827ef8fe167301d2638ac9ddb96c"
            },
            "high_sierra": {
              "url": "https://homebrew.bintray.com/bottles/tcl-tk-8.6.10.high_sierra.bottle.1.tar.gz",
              "sha256": "d1d689cc3e9cf08b2a42d487db3c4142e7ee4ff322bef22d6187fc67a5b776b7"
            }
          }
        }
      },
      "wakeonlan": {
        "version": "0.41",
        "bottle": {
          "cellar": ":any_skip_relocation",
          "prefix": "/usr/local",
          "files": {
            "catalina": {
              "url": "https://homebrew.bintray.com/bottles/wakeonlan-0.41.catalina.bottle.tar.gz",
              "sha256": "017f70ad18520de448fa1e31d0e53d4b52ad548518da6923808b85d850bf3ee4"
            },
            "mojave": {
              "url": "https://homebrew.bintray.com/bottles/wakeonlan-0.41.mojave.bottle.tar.gz",
              "sha256": "5fc2054a08a4ce9d08b5d004917acb1b57b198611f693503fca252550778a90b"
            },
            "high_sierra": {
              "url": "https://homebrew.bintray.com/bottles/wakeonlan-0.41.high_sierra.bottle.tar.gz",
              "sha256": "876e4fd4919523eb2db07159a7c7d82fa30bec74972f0ef69c55588831db8a4d"
            },
            "sierra": {
              "url": "https://homebrew.bintray.com/bottles/wakeonlan-0.41.sierra.bottle.tar.gz",
              "sha256": "2cb19ca9617f87fc2c14536434f17b44174336a739fed3ad83404ccfb412ee31"
            },
            "el_capitan": {
              "url": "https://homebrew.bintray.com/bottles/wakeonlan-0.41.el_capitan.bottle.tar.gz",
              "sha256": "7da7f512ae921016be21fa3899d4f01841e3da5bc96570fcd85b530e4e720c06"
            },
            "yosemite": {
              "url": "https://homebrew.bintray.com/bottles/wakeonlan-0.41.yosemite.bottle.tar.gz",
              "sha256": "78a5d905b250ddb09cc3fa4296f2ffc8c925788a7d8e5d05e96f5581e81a7e9d"
            },
            "mavericks": {
              "url": "https://homebrew.bintray.com/bottles/wakeonlan-0.41.mavericks.bottle.tar.gz",
              "sha256": "0669ec3967a728dd2962727896711f418556491ad172483240e84110843998e0"
            }
          }
        }
      },
      "wget": {
        "version": "1.20.3_2",
        "bottle": {
          "cellar": "/usr/local/Cellar",
          "prefix": "/usr/local",
          "files": {
            "catalina": {
              "url": "https://homebrew.bintray.com/bottles/wget-1.20.3_2.catalina.bottle.tar.gz",
              "sha256": "ef65c759c5097a36323fa9c77756468649e8d1980a3a4e05695c05e39568967c"
            },
            "mojave": {
              "url": "https://homebrew.bintray.com/bottles/wget-1.20.3_2.mojave.bottle.tar.gz",
              "sha256": "28f4090610946a4eb207df102d841de23ced0d06ba31cb79e040d883906dcd4f"
            },
            "high_sierra": {
              "url": "https://homebrew.bintray.com/bottles/wget-1.20.3_2.high_sierra.bottle.tar.gz",
              "sha256": "91dd0caca9bd3f38c439d5a7b6f68440c4274945615fae035ff0a369264b8a2f"
            }
          }
        }
      },
      "youtube-dl": {
        "version": "2020.07.28",
        "bottle": false
      },
      "zlib": {
        "version": "1.2.11",
        "bottle": {
          "cellar": ":any",
          "prefix": "/usr/local",
          "files": {
            "catalina": {
              "url": "https://homebrew.bintray.com/bottles/zlib-1.2.11.catalina.bottle.tar.gz",
              "sha256": "8ec66cf6faa310712767efc3022fdd16568a79234439f64bf579acb628f893bc"
            },
            "mojave": {
              "url": "https://homebrew.bintray.com/bottles/zlib-1.2.11.mojave.bottle.tar.gz",
              "sha256": "245a43a59c57f83848e7382974bb80a46eac1d53bcaefb1bdebd1f85107d4169"
            },
            "high_sierra": {
              "url": "https://homebrew.bintray.com/bottles/zlib-1.2.11.high_sierra.bottle.tar.gz",
              "sha256": "30548658b43cf66979f2756680fbb32d3c19c967e478ceea22d07f536b22bbce"
            },
            "sierra": {
              "url": "https://homebrew.bintray.com/bottles/zlib-1.2.11.sierra.bottle.tar.gz",
              "sha256": "f822b4dbab4a15b889316b89248c7b4d15d6af9dc460bf209b9425b0accb7fa3"
            },
            "el_capitan": {
              "url": "https://homebrew.bintray.com/bottles/zlib-1.2.11.el_capitan.bottle.tar.gz",
              "sha256": "3f912f6f1ce6c586128ebde29756c883b89409e652ca7aa9a29a773c2d4d0915"
            },
            "yosemite": {
              "url": "https://homebrew.bintray.com/bottles/zlib-1.2.11.yosemite.bottle.tar.gz",
              "sha256": "5b969eb38b90a3e31869586df9d62e59d359212b16c6a270aee690dd67caa491"
            }
          }
        }
      },
      "d12frosted/emacs-plus/emacs-plus@27": {
        "options": {
          "args": [
            "HEAD",
            "with-jansson",
            "with-modern-black-variant-icon"
          ]
        }
      },
      "github/gh/gh": null,
      "jawshooah/pyenv/pyenv-default-packages": {
        "options": {
          "args": [
            "HEAD"
          ]
        }
      },
      "openblas": {
        "version": "0.3.10_1",
        "bottle": {
          "cellar": ":any",
          "prefix": "/usr/local",
          "files": {
            "catalina": {
              "url": "https://homebrew.bintray.com/bottles/openblas-0.3.10_1.catalina.bottle.tar.gz",
              "sha256": "dcffce6b09f1710f3b620122c67a31aea99073ef036a9abf2e8261a999c5cbb5"
            },
            "mojave": {
              "url": "https://homebrew.bintray.com/bottles/openblas-0.3.10_1.mojave.bottle.tar.gz",
              "sha256": "cf345fcf861d1a699832126476a7385b9cc212dc5b1b985749e219481473e836"
            },
            "high_sierra": {
              "url": "https://homebrew.bintray.com/bottles/openblas-0.3.10_1.high_sierra.bottle.tar.gz",
              "sha256": "09e6222e227fccb3d1a86aa0b0ac77fec3e512ba9266ecf72f235c58c6795009"
            }
          }
        }
      },
      "fftw": {
        "version": "3.3.8_2",
        "bottle": {
          "cellar": ":any",
          "prefix": "/usr/local",
          "files": {
            "catalina": {
              "url": "https://homebrew.bintray.com/bottles/fftw-3.3.8_2.catalina.bottle.tar.gz",
              "sha256": "e021f210b7f8a785b86b82fe191408d783def6e6baec192e8133d703c51bf0de"
            },
            "mojave": {
              "url": "https://homebrew.bintray.com/bottles/fftw-3.3.8_2.mojave.bottle.tar.gz",
              "sha256": "d4af1ee10e2eb5784874cac832f10d3e8d3010962e31102df7c6bffc34783d92"
            },
            "high_sierra": {
              "url": "https://homebrew.bintray.com/bottles/fftw-3.3.8_2.high_sierra.bottle.tar.gz",
              "sha256": "64d050b8736eed9b127f175d39d4acc93c1ec960b096aee756bbb5ea906b6b82"
            }
          }
        }
      },
      "hdf5": {
        "version": "1.12.0_1",
        "bottle": {
          "cellar": ":any",
          "prefix": "/usr/local",
          "files": {
            "catalina": {
              "url": "https://homebrew.bintray.com/bottles/hdf5-1.12.0_1.catalina.bottle.tar.gz",
              "sha256": "e0990f7a52f3f66fd8d546ff1e1d26d4a0cec5ebc9a45ec21fb5335359d6878a"
            },
            "mojave": {
              "url": "https://homebrew.bintray.com/bottles/hdf5-1.12.0_1.mojave.bottle.tar.gz",
              "sha256": "3b681a12f21a576b4c80d84d52dbe8ff9380ecc517f9b742dbe26faf5ffc289a"
            },
            "high_sierra": {
              "url": "https://homebrew.bintray.com/bottles/hdf5-1.12.0_1.high_sierra.bottle.tar.gz",
              "sha256": "331f9a49fb5abb3344a6dc7ff626e37d799418d8de507487c30aff91e2b22265"
            }
          }
        }
      }
    }
  },
  "system": {
    "macos": {
      "catalina": {
        "HOMEBREW_VERSION": "2.4.13",
        "HOMEBREW_PREFIX": "/usr/local",
        "Homebrew/homebrew-core": "085791ecf990b7dfe53173fc0669dd984648e9c1",
        "CLT": "1103.0.32.62",
        "Xcode": "11.6",
        "macOS": "10.15.6"
      }
    }
  }
}
